findiff/__init__.py
findiff/config.py
findiff/data.py
findiff/dataio.py
findiff/gen.py
findiff/guard.py
findiff/logging_util.py
findiff/metrics.py
findiff/mix.py
findiff/pipeline.py
findiff/plotting.py
findiff/reporting.py
findiff/score.py
findiff/stats.py
findiff/train.py
findiff/validators.py
findiff/version.py
findiff/utils/io.py
findiff/utils/logging.py
findiff_finance-0.1.0.dist-info/METADATA
findiff_finance-0.1.0.dist-info/WHEEL
findiff_finance-0.1.0.dist-info/top_level.txt
findiff_finance-0.1.0.dist-info/RECORD
