Metadata-Version: 2.4
Name: findiff-finance
Version: 0.1.0
Summary: FinDiff: diffusion-based, teacher-aligned augmentation for time-series finance
Author: FinDiff
License: Apache-2.0
Project-URL: Homepage, https://github.com/yanlinc0106/FinDiff
Classifier: Programming Language :: Python :: 3
Classifier: License :: OSI Approved :: Apache Software License
Classifier: Operating System :: OS Independent
Classifier: Intended Audience :: Science/Research
Classifier: Topic :: Scientific/Engineering :: Artificial Intelligence
Classifier: Topic :: Office/Business :: Financial :: Investment
Requires-Python: >=3.9
Requires-Dist: numpy>=1.24
Requires-Dist: pandas>=2.0
Requires-Dist: scikit-learn>=1.3
Requires-Dist: torch>=2.1
Requires-Dist: tqdm>=4.66
Requires-Dist: pyyaml>=6.0
Requires-Dist: matplotlib>=3.8
Provides-Extra: dev
Requires-Dist: pytest>=7.4; extra == "dev"
Requires-Dist: pytest-cov>=4.1; extra == "dev"
Requires-Dist: ruff>=0.6.2; extra == "dev"
Requires-Dist: black>=24.8.0; extra == "dev"
Requires-Dist: mypy>=1.10.0; extra == "dev"
